upflame/__init__.py
upflame/__main__.py
upflame/core/greet.py
upflame/core/upflame_core.py
upflame/info/project_info.py
upflame-0.1.0.dist-info/entry_points.txt
upflame-0.1.0.dist-info/licenses/LICENSE
upflame-0.1.0.dist-info/METADATA
upflame-0.1.0.dist-info/WHEEL
upflame-0.1.0.dist-info/RECORD
