Metadata-Version: 2.4
Name: upflame
Version: 0.1.0
Summary: Upflame Labs core packages with pretty print features.
License: MIT
License-File: LICENSE
Author: Victor Amit
Author-email: dev@amit.work
Requires-Python: >=3.9
Classifier: License :: OSI Approved :: MIT License
Classifier: Programming Language :: Python :: 3
Classifier: Programming Language :: Python :: 3.9
Classifier: Programming Language :: Python :: 3.10
Classifier: Programming Language :: Python :: 3.11
Classifier: Programming Language :: Python :: 3.12
Classifier: Programming Language :: Python :: 3.13
Classifier: Programming Language :: Python :: 3.14
Project-URL: documentation, https://github.com/upflame/upflame#readme
Project-URL: homepage, https://github.com/upflame/upflame
Project-URL: repository, https://github.com/upflame/upflame
